lan_presenter/__init__.py
lan_presenter/__main__.py
lan_presenter/index.html
lan_presenter-0.2.0.dist-info/LICENSE
lan_presenter-0.2.0.dist-info/METADATA
lan_presenter-0.2.0.dist-info/WHEEL
lan_presenter-0.2.0.dist-info/entry_points.txt
lan_presenter-0.2.0.dist-info/top_level.txt
lan_presenter-0.2.0.dist-info/RECORD
