Metadata-Version: 2.1
Name: lan-presenter
Version: 0.2.0
Summary: Presenter remote control over local network connection
Home-page: https://github.com/tiborhari/lan-presenter/
Author: Tibor Hári
Author-email: hartib@gmail.com
License: UNKNOWN
Platform: UNKNOWN
Requires-Python: >=3.6, <4
License-File: LICENSE
Requires-Dist: aiohttp (~=3.8.1)
Requires-Dist: keyboard (~=0.13.5)
Requires-Dist: qrcode (~=7.3.1)
Provides-Extra: dev
Requires-Dist: flake8 (==3.7.9) ; extra == 'dev'
